{"v":"5.1.13","fr":29.9700012207031,"ip":0,"op":85.000003462121,"w":1500,"h":800,"nm":"loading","ddd":0,"assets":[],"layers":[{"ddd":0,"ind":2,"ty":4,"nm":"logo Outlines","sr":1,"ks":{"o":{"a":0,"k":100,"ix":11},"r":{"a":0,"k":0,"ix":10},"p":{"a":1,"k":[{"i":{"x":0.93,"y":0.934},"o":{"x":0.676,"y":0},"n":"0p93_0p934_0p676_0","t":0,"s":[754,-80,0],"e":[754,456.914,0],"to":[0,47.1975631713867,0],"ti":[0,0,0]},{"i":{"x":0.326,"y":1},"o":{"x":0.381,"y":1},"n":"0p326_1_0p381_1","t":30,"s":[754,456.914,0],"e":[754,489.914,0],"to":[0,0,0],"ti":[0,0,0]},{"i":{"x":0,"y":1},"o":{"x":0.285,"y":0},"n":"0_1_0p285_0","t":35,"s":[754,489.914,0],"e":[754,260.914,0],"to":[0,0,0],"ti":[0,-61.6809501647949,0]},{"i":{"x":0.771,"y":0.807},"o":{"x":0.823,"y":0},"n":"0p771_0p807_0p823_0","t":55,"s":[754,260.914,0],"e":[754,860,0],"to":[0,61.6809501647949,0],"ti":[0,-99.8476181030273,0]},{"t":85.000003462121}],"ix":2},"a":{"a":0,"k":[78.949,87.336,0],"ix":1},"s":{"a":0,"k":[60,60,100],"ix":6}},"ao":0,"shapes":[{"ty":"gr","it":[{"ind":0,"ty":"sh","ix":1,"ks":{"a":0,"k":{"i":[[38.732,0],[0,-38.732],[-38.732,0],[0,38.733]],"o":[[-38.732,0],[0,38.733],[38.732,0],[0,-38.732]],"v":[[0,-70.132],[-70.132,0],[0,70.132],[70.132,0]],"c":true},"ix":2},"nm":"Path 1","mn":"ADBE Vector Shape - Group","hd":false},{"ind":1,"ty":"sh","ix":2,"ks":{"a":0,"k":{"i":[[-7.827,0],[-7.135,-3.018],[-5.326,-5.326],[-2.918,-6.899],[0,-7.827],[3.017,-7.136],[5.325,-5.325],[6.898,-2.917],[7.828,0],[7.136,3.018],[5.325,5.325],[2.918,6.898],[0,7.828],[-3.018,7.135],[-5.325,5.325],[-6.898,2.918]],"o":[[7.828,0],[6.898,2.918],[5.325,5.325],[3.017,7.135],[0,7.828],[-2.918,6.898],[-5.326,5.325],[-7.135,3.018],[-7.827,0],[-6.898,-2.917],[-5.325,-5.325],[-3.018,-7.136],[0,-7.827],[2.918,-6.899],[5.325,-5.326],[7.136,-3.018]],"v":[[0,-57.942],[22.549,-53.395],[40.971,-40.971],[53.395,-22.549],[57.941,0],[53.395,22.551],[40.971,40.971],[22.549,53.394],[0,57.943],[-22.551,53.394],[-40.971,40.971],[-53.395,22.551],[-57.943,0],[-53.395,-22.549],[-40.971,-40.971],[-22.551,-53.395]],"c":true},"ix":2},"nm":"Path 2","mn":"ADBE Vector Shape - Group","hd":false},{"ty":"mm","mm":1,"nm":"Merge Paths 1","mn":"ADBE Vector Filter - Merge","hd":false},{"ty":"fl","c":{"a":0,"k":[0.349000010771,0.356999984442,0.941000007181,1],"ix":4},"o":{"a":0,"k":100,"ix":5},"r":1,"nm":"Fill 1","mn":"ADBE Vector Graphic - Fill","hd":false},{"ty":"tr","p":{"a":0,"k":[70.382,104.291],"ix":2},"a":{"a":0,"k":[0,0],"ix":1},"s":{"a":0,"k":[100,100],"ix":3},"r":{"a":0,"k":0,"ix":6},"o":{"a":0,"k":100,"ix":7},"sk":{"a":0,"k":0,"ix":4},"sa":{"a":0,"k":0,"ix":5},"nm":"Transform"}],"nm":"Group 1","np":4,"cix":2,"ix":1,"mn":"ADBE Vector Group","hd":false},{"ty":"gr","it":[{"ind":0,"ty":"sh","ix":1,"ks":{"a":0,"k":{"i":[[0,-3.302],[2.002,-0.965],[4.705,-0.113],[0.257,0],[5.087,2.738],[0.213,0.305],[0,0],[-6.127,-3.186],[-3.565,0.126],[-3.041,1.393],[-0.071,0.032],[-0.028,0.012],[-0.827,0]],"o":[[0,2.373],[-4.669,2.177],[-0.258,0.007],[-5.437,0],[-8.747,-4.706],[0,0],[0.276,0.381],[3.444,1.791],[2.915,-0.099],[0.072,-0.032],[0.029,-0.014],[0.715,-0.303],[3.302,0]],"v":[[24.068,2.741],[20.683,8.129],[6.593,11.575],[5.819,11.586],[-10.035,7.461],[-24.068,-4.771],[-14.245,-11.586],[-4.044,-2.894],[6.518,-0.384],[15.468,-2.631],[15.681,-2.729],[15.763,-2.767],[18.09,-3.237]],"c":true},"ix":2},"nm":"Path 1","mn":"ADBE Vector Shape - Group","hd":false},{"ty":"fl","c":{"a":0,"k":[0.991999966491,0.630999995213,0.74900004069,1],"ix":4},"o":{"a":0,"k":100,"ix":5},"r":1,"nm":"Fill 1","mn":"ADBE Vector Graphic - Fill","hd":false},{"ty":"tr","p":{"a":0,"k":[133.581,155.072],"ix":2},"a":{"a":0,"k":[0,0],"ix":1},"s":{"a":0,"k":[100,100],"ix":3},"r":{"a":0,"k":0,"ix":6},"o":{"a":0,"k":100,"ix":7},"sk":{"a":0,"k":0,"ix":4},"sa":{"a":0,"k":0,"ix":5},"nm":"Transform"}],"nm":"Group 2","np":2,"cix":2,"ix":2,"mn":"ADBE Vector Group","hd":false},{"ty":"gr","it":[{"ind":0,"ty":"sh","ix":1,"ks":{"a":0,"k":{"i":[[0,-3.252],[1.972,-0.95],[4.634,-0.112],[0.253,0],[5.011,2.697],[0.21,0.3],[0,0],[-6.036,-3.138],[-3.512,0.124],[-2.995,1.373],[-0.07,0.032],[-0.027,0.012],[-0.814,0]],"o":[[0,2.337],[-4.599,2.145],[-0.255,0.006],[-5.353,0],[-8.616,-4.635],[0,0],[0.271,0.375],[3.393,1.764],[2.871,-0.098],[0.072,-0.031],[0.028,-0.013],[0.704,-0.298],[3.252,0]],"v":[[23.707,2.699],[20.372,8.007],[6.495,11.402],[5.73,11.411],[-9.884,7.349],[-23.707,-4.699],[-14.03,-11.411],[-3.983,-2.85],[6.421,-0.378],[15.236,-2.592],[15.445,-2.688],[15.526,-2.725],[17.819,-3.188]],"c":true},"ix":2},"nm":"Path 1","mn":"ADBE Vector Shape - Group","hd":false},{"ty":"fl","c":{"a":0,"k":[0.991999966491,0.630999995213,0.74900004069,1],"ix":4},"o":{"a":0,"k":100,"ix":5},"r":1,"nm":"Fill 1","mn":"ADBE Vector Graphic - Fill","hd":false},{"ty":"tr","p":{"a":0,"k":[133.942,155.336],"ix":2},"a":{"a":0,"k":[0,0],"ix":1},"s":{"a":0,"k":[100,100],"ix":3},"r":{"a":0,"k":0,"ix":6},"o":{"a":0,"k":100,"ix":7},"sk":{"a":0,"k":0,"ix":4},"sa":{"a":0,"k":0,"ix":5},"nm":"Transform"}],"nm":"Group 3","np":2,"cix":2,"ix":3,"mn":"ADBE Vector Group","hd":false},{"ty":"gr","it":[{"ind":0,"ty":"sh","ix":1,"ks":{"a":0,"k":{"i":[[21.854,0],[12.853,-15.676],[-21.847,0],[-12.863,15.661]],"o":[[-21.853,0],[12.862,15.661],[21.848,0],[-12.854,-15.676]],"v":[[0,-25.666],[-54.223,0.013],[0,25.666],[54.223,0.013]],"c":true},"ix":2},"nm":"Path 1","mn":"ADBE Vector Shape - Group","hd":false},{"ind":1,"ty":"sh","ix":2,"ks":{"a":0,"k":{"i":[[-15.57,0],[-11.204,-10.492],[15.565,0],[11.207,10.482]],"o":[[15.57,0],[-11.208,10.482],[-15.565,0],[11.203,-10.492]],"v":[[0,-16.373],[41.517,0.008],[0,16.373],[-41.517,0.008]],"c":true},"ix":2},"nm":"Path 2","mn":"ADBE Vector Shape - Group","hd":false},{"ty":"mm","mm":1,"nm":"Merge Paths 1","mn":"ADBE Vector Filter - Merge","hd":false},{"ty":"fl","c":{"a":0,"k":[0.991999966491,0.630999995213,0.74900004069,1],"ix":4},"o":{"a":0,"k":100,"ix":5},"r":1,"nm":"Fill 1","mn":"ADBE Vector Graphic - Fill","hd":false},{"ty":"tr","p":{"a":0,"k":[70.382,148.756],"ix":2},"a":{"a":0,"k":[0,0],"ix":1},"s":{"a":0,"k":[100,100],"ix":3},"r":{"a":0,"k":0,"ix":6},"o":{"a":0,"k":100,"ix":7},"sk":{"a":0,"k":0,"ix":4},"sa":{"a":0,"k":0,"ix":5},"nm":"Transform"}],"nm":"Group 4","np":4,"cix":2,"ix":4,"mn":"ADBE Vector Group","hd":false},{"ty":"gr","it":[{"ind":0,"ty":"sh","ix":1,"ks":{"a":0,"k":{"i":[[-11.479,-8.939],[-0.076,0.319],[0,0],[0.017,0.304],[0,2.845],[3.421,0],[0,-3.604],[-1.411,-1.2],[0,0],[2.945,0],[2.07,2.924],[0,0],[0.001,0.004],[0,1.748],[3.42,0],[0,-3.607],[-1.123,-1.184],[0,0],[3.451,0],[2.057,2.185],[0,0],[0,2.032],[3.418,0],[0,-3.604],[-2.513,-0.835],[-0.074,-0.318],[0,0],[-0.093,-0.198],[-15.649,0]],"o":[[0.158,-0.269],[0,0],[0.072,-0.308],[2.412,-0.898],[0,-3.604],[-3.418,0],[0,2.056],[0,0],[-2.082,2.198],[-3.461,0],[0,0],[-0.004,-0.005],[1.063,-1.176],[0,-3.607],[-3.421,0],[0,1.802],[0,0],[-2.071,2.895],[-2.918,0],[0,0],[1.38,-1.201],[0,-3.604],[-3.421,0],[0,2.924],[-0.019,0.314],[0,0],[0.052,0.221],[11.47,-8.909],[15.677,0]],"v":[[41.589,26.355],[41.946,25.473],[48.442,-1.933],[48.519,-2.857],[52.663,-9.021],[46.462,-15.559],[40.261,-9.021],[42.577,-3.93],[34.391,4.701],[26.596,8.107],[17.761,3.44],[4.492,-15.29],[4.481,-15.304],[6.202,-19.815],[0.001,-26.355],[-6.202,-19.815],[-4.383,-15.194],[-17.751,3.485],[-26.564,8.107],[-34.39,4.671],[-42.523,-3.972],[-40.261,-9.021],[-46.46,-15.559],[-52.663,-9.021],[-48.322,-2.783],[-48.244,-1.831],[-41.747,25.678],[-41.525,26.307],[0.001,12.09]],"c":true},"ix":2},"nm":"Path 1","mn":"ADBE Vector Shape - Group","hd":false},{"ty":"fl","c":{"a":0,"k":[0.991999966491,0.630999995213,0.74900004069,1],"ix":4},"o":{"a":0,"k":100,"ix":5},"r":1,"nm":"Fill 1","mn":"ADBE Vector Graphic - Fill","hd":false},{"ty":"tr","p":{"a":0,"k":[70.718,26.606],"ix":2},"a":{"a":0,"k":[0,0],"ix":1},"s":{"a":0,"k":[100,100],"ix":3},"r":{"a":0,"k":0,"ix":6},"o":{"a":0,"k":100,"ix":7},"sk":{"a":0,"k":0,"ix":4},"sa":{"a":0,"k":0,"ix":5},"nm":"Transform"}],"nm":"Group 5","np":2,"cix":2,"ix":5,"mn":"ADBE Vector Group","hd":false}],"ip":0,"op":85.000003462121,"st":0,"bm":0},{"ddd":0,"ind":3,"ty":4,"nm":"eraser Outlines","sr":1,"ks":{"o":{"a":0,"k":100,"ix":11},"r":{"a":1,"k":[{"i":{"x":[0.667],"y":[1]},"o":{"x":[0.333],"y":[0]},"n":["0p667_1_0p333_0"],"t":50,"s":[0],"e":[-30]},{"i":{"x":[0.833],"y":[0.833]},"o":{"x":[0.167],"y":[0.167]},"n":["0p833_0p833_0p167_0p167"],"t":60,"s":[-30],"e":[-30]},{"i":{"x":[0.833],"y":[0.833]},"o":{"x":[0.167],"y":[0.167]},"n":["0p833_0p833_0p167_0p167"],"t":73,"s":[-30],"e":[0]},{"t":75.0000030548126}],"ix":10},"p":{"a":1,"k":[{"i":{"x":0.667,"y":0.667},"o":{"x":0.167,"y":0.167},"n":"0p667_0p667_0p167_0p167","t":0,"s":[535.5,426.841,0],"e":[535.5,426.841,0],"to":[0,0,0],"ti":[0,0,0]},{"i":{"x":0.667,"y":1},"o":{"x":0.333,"y":0},"n":"0p667_1_0p333_0","t":50,"s":[535.5,426.841,0],"e":[905.5,458.841,0],"to":[61.6666679382324,5.33333349227905,0],"ti":[-68.1666641235352,-40.3333320617676,0]},{"i":{"x":0.833,"y":0.833},"o":{"x":0.167,"y":0.167},"n":"0p833_0p833_0p167_0p167","t":60,"s":[905.5,458.841,0],"e":[533.762,460.124,0],"to":[44.4354553222656,3.81215691566467,0],"ti":[103.765007019043,8.90209197998047,0]},{"i":{"x":0.833,"y":0.833},"o":{"x":0.167,"y":0.167},"n":"0p833_0p833_0p167_0p167","t":73,"s":[533.762,460.124,0],"e":[535.5,426.841,0],"to":[-22.41237449646,-1.9227774143219,0],"ti":[1.44472503662109,0.12394424527884,0]},{"t":75.0000030548126}],"ix":2},"a":{"a":0,"k":[26,109.159,0],"ix":1},"s":{"a":0,"k":[60,60,100],"ix":6}},"ao":0,"shapes":[{"ty":"gr","it":[{"ind":0,"ty":"sh","ix":1,"ks":{"a":0,"k":{"i":[[1.104,0],[0,0],[0,1.104],[0,0],[-1.104,0],[0,0],[0,-1.105],[0,0]],"o":[[0,0],[-1.104,0],[0,0],[0,-1.105],[0,0],[1.104,0],[0,0],[0,1.104]],"v":[[23,82.534],[-23,82.534],[-25,80.534],[-25,-80.534],[-23,-82.534],[23,-82.534],[25,-80.534],[25,80.534]],"c":true},"ix":2},"nm":"Path 1","mn":"ADBE Vector Shape - Group","hd":false},{"ty":"fl","c":{"a":0,"k":[0.991999966491,0.630999995213,0.74900004069,1],"ix":4},"o":{"a":0,"k":100,"ix":5},"r":1,"nm":"Fill 1","mn":"ADBE Vector Graphic - Fill","hd":false},{"ty":"tr","p":{"a":0,"k":[26,82.784],"ix":2},"a":{"a":0,"k":[0,0],"ix":1},"s":{"a":0,"k":[100,100],"ix":3},"r":{"a":0,"k":0,"ix":6},"o":{"a":0,"k":100,"ix":7},"sk":{"a":0,"k":0,"ix":4},"sa":{"a":0,"k":0,"ix":5},"nm":"Transform"}],"nm":"Group 1","np":2,"cix":2,"ix":1,"mn":"ADBE Vector Group","hd":false},{"ty":"gr","it":[{"ind":0,"ty":"sh","ix":1,"ks":{"a":0,"k":{"i":[[1.104,0],[0,0],[0,1.104],[0,0],[-1.104,0],[0,0],[0,-1.104],[0,0]],"o":[[0,0],[-1.104,0],[0,0],[0,-1.104],[0,0],[1.104,0],[0,0],[0,1.104]],"v":[[14,64],[-14,64],[-16,62],[-16,-62],[-14,-64],[14,-64],[16,-62],[16,62]],"c":true},"ix":2},"nm":"Path 1","mn":"ADBE Vector Shape - Group","hd":false},{"ty":"st","c":{"a":0,"k":[0.933000033509,0.933000033509,0.933000033509,1],"ix":3},"o":{"a":0,"k":100,"ix":4},"w":{"a":0,"k":4,"ix":5},"lc":1,"lj":1,"ml":10,"nm":"Stroke 1","mn":"ADBE Vector Graphic - Stroke","hd":false},{"ty":"fl","c":{"a":0,"k":[0.972999961703,0.972999961703,0.972999961703,1],"ix":4},"o":{"a":0,"k":100,"ix":5},"r":1,"nm":"Fill 1","mn":"ADBE Vector Graphic - Fill","hd":false},{"ty":"tr","p":{"a":0,"k":[26,144.318],"ix":2},"a":{"a":0,"k":[0,0],"ix":1},"s":{"a":0,"k":[100,100],"ix":3},"r":{"a":0,"k":0,"ix":6},"o":{"a":0,"k":100,"ix":7},"sk":{"a":0,"k":0,"ix":4},"sa":{"a":0,"k":0,"ix":5},"nm":"Transform"}],"nm":"Group 2","np":3,"cix":2,"ix":2,"mn":"ADBE Vector Group","hd":false}],"ip":0,"op":85.000003462121,"st":0,"bm":0},{"ddd":0,"ind":4,"ty":4,"nm":"pen Outlines","sr":1,"ks":{"o":{"a":0,"k":100,"ix":11},"r":{"a":1,"k":[{"i":{"x":[0.667],"y":[1]},"o":{"x":[0.333],"y":[0]},"n":["0p667_1_0p333_0"],"t":0,"s":[0],"e":[30]},{"i":{"x":[0.833],"y":[0.833]},"o":{"x":[0.167],"y":[0.167]},"n":["0p833_0p833_0p167_0p167"],"t":10,"s":[30],"e":[30]},{"i":{"x":[0.833],"y":[0.833]},"o":{"x":[0.167],"y":[0.167]},"n":["0p833_0p833_0p167_0p167"],"t":23,"s":[30],"e":[0]},{"t":25.0000010182709}],"ix":10},"p":{"a":1,"k":[{"i":{"x":0.667,"y":1},"o":{"x":0.333,"y":0},"n":"0p667_1_0p333_0","t":0,"s":[964,421.854,0],"e":[590.5,458.854,0],"to":[-62.25,6.16665840148926,0],"ti":[0,0,0]},{"i":{"x":0.833,"y":0.833},"o":{"x":0.167,"y":0.167},"n":"0p833_0p833_0p167_0p167","t":10,"s":[590.5,458.854,0],"e":[959.15,458.854,0],"to":[0,0,0],"ti":[0,0,0]},{"i":{"x":0.833,"y":0.833},"o":{"x":0.167,"y":0.167},"n":"0p833_0p833_0p167_0p167","t":23,"s":[959.15,458.854,0],"e":[964,421.854,0],"to":[0,0,0],"ti":[-8.05009746551514,0.83083182573318,0]},{"t":25.0000010182709}],"ix":2},"a":{"a":0,"k":[25.303,104.172,0],"ix":1},"s":{"a":0,"k":[60,60,100],"ix":6}},"ao":0,"shapes":[{"ty":"gr","it":[{"ind":0,"ty":"sh","ix":1,"ks":{"a":0,"k":{"i":[[1.092,0],[0,0],[0.018,1.092],[0,0],[-1.117,0],[0,0],[0.017,-1.117],[0,0]],"o":[[0,0],[-1.092,0],[0,0],[-0.017,-1.117],[0,0],[1.117,0],[0,0],[-0.018,1.092]],"v":[[16.689,59.957],[-16.688,59.957],[-18.688,57.989],[-20.539,-57.925],[-18.539,-59.957],[18.539,-59.957],[20.539,-57.925],[18.689,57.989]],"c":true},"ix":2},"nm":"Path 1","mn":"ADBE Vector Shape - Group","hd":false},{"ty":"fl","c":{"a":0,"k":[0.349000010771,0.356999984442,0.941000007181,1],"ix":4},"o":{"a":0,"k":100,"ix":5},"r":1,"nm":"Fill 1","mn":"ADBE Vector Graphic - Fill","hd":false},{"ty":"tr","p":{"a":0,"k":[25.302,60.207],"ix":2},"a":{"a":0,"k":[0,0],"ix":1},"s":{"a":0,"k":[100,100],"ix":3},"r":{"a":0,"k":0,"ix":6},"o":{"a":0,"k":100,"ix":7},"sk":{"a":0,"k":0,"ix":4},"sa":{"a":0,"k":0,"ix":5},"nm":"Transform"}],"nm":"Group 1","np":2,"cix":2,"ix":1,"mn":"ADBE Vector Group","hd":false},{"ty":"gr","it":[{"ind":0,"ty":"sh","ix":1,"ks":{"a":0,"k":{"i":[[0.152,-0.975],[0,0],[-0.243,-0.487],[0,0],[0,0],[-0.037,3.064],[-3.808,0.056],[0,-3.99],[2.658,-1.05],[0,0],[0,0],[0.084,0.538],[0,0],[0.985,0.002],[0,0]],"o":[[0,0],[-0.084,0.538],[0,0],[0,0],[-2.683,-1.06],[0.046,-3.809],[4.002,-0.061],[0,3.026],[0,0],[0,0],[0.243,-0.487],[0,0],[-0.152,-0.973],[0,0],[-0.986,-0.002]],"v":[[-18.938,-41.341],[-24.969,-2.746],[-24.724,-1.169],[-2.622,43.034],[-2.622,-8.264],[-7.167,-15.017],[-0.109,-22.095],[7.167,-14.928],[2.622,-8.264],[2.622,43.034],[24.724,-1.169],[24.969,-2.746],[18.945,-41.293],[16.972,-42.985],[-16.96,-43.032]],"c":true},"ix":2},"nm":"Path 1","mn":"ADBE Vector Shape - Group","hd":false},{"ty":"fl","c":{"a":0,"k":[0.26699999641,0.26699999641,0.26699999641,1],"ix":4},"o":{"a":0,"k":100,"ix":5},"r":1,"nm":"Fill 1","mn":"ADBE Vector Graphic - Fill","hd":false},{"ty":"tr","p":{"a":0,"k":[25.303,165.06],"ix":2},"a":{"a":0,"k":[0,0],"ix":1},"s":{"a":0,"k":[100,100],"ix":3},"r":{"a":0,"k":0,"ix":6},"o":{"a":0,"k":100,"ix":7},"sk":{"a":0,"k":0,"ix":4},"sa":{"a":0,"k":0,"ix":5},"nm":"Transform"}],"nm":"Group 2","np":2,"cix":2,"ix":2,"mn":"ADBE Vector Group","hd":false}],"ip":0,"op":85.000003462121,"st":0,"bm":0},{"ddd":0,"ind":5,"ty":4,"nm":"line reveal","td":1,"sr":1,"ks":{"o":{"a":0,"k":100,"ix":11},"r":{"a":0,"k":0,"ix":10},"p":{"a":1,"k":[{"i":{"x":0.833,"y":0.833},"o":{"x":0.167,"y":0.167},"n":"0p833_0p833_0p167_0p167","t":10,"s":[361.426,511.856,0],"e":[750.426,511.856,0],"to":[64.8333358764648,0,0],"ti":[0,0,0]},{"i":{"x":0.833,"y":0.833},"o":{"x":0.167,"y":0.167},"n":"0p833_0p833_0p167_0p167","t":23,"s":[750.426,511.856,0],"e":[754.426,511.856,0],"to":[0,0,0],"ti":[0,0,0]},{"i":{"x":0.833,"y":0.833},"o":{"x":0.167,"y":0.167},"n":"0p833_0p833_0p167_0p167","t":60,"s":[754.426,511.856,0],"e":[361.426,511.856,0],"to":[0,0,0],"ti":[65.5,0,0]},{"t":73.000002973351}],"ix":2},"a":{"a":0,"k":[0.426,111.856,0],"ix":1},"s":{"a":0,"k":[100,100,100],"ix":6}},"ao":0,"shapes":[{"ty":"gr","it":[{"ty":"rc","d":1,"s":{"a":0,"k":[380.852,70],"ix":2},"p":{"a":0,"k":[0,0],"ix":3},"r":{"a":0,"k":0,"ix":4},"nm":"Rectangle Path 1","mn":"ADBE Vector Shape - Rect","hd":false},{"ty":"fl","c":{"a":0,"k":[0.056019999934,0.528845035329,0.410638996199,1],"ix":4},"o":{"a":0,"k":100,"ix":5},"r":1,"nm":"Fill 1","mn":"ADBE Vector Graphic - Fill","hd":false},{"ty":"tr","p":{"a":0,"k":[0.426,111.856],"ix":2},"a":{"a":0,"k":[0,0],"ix":1},"s":{"a":0,"k":[100,100],"ix":3},"r":{"a":0,"k":0,"ix":6},"o":{"a":0,"k":100,"ix":7},"sk":{"a":0,"k":0,"ix":4},"sa":{"a":0,"k":0,"ix":5},"nm":"Transform"}],"nm":"Rectangle 1","np":3,"cix":2,"ix":1,"mn":"ADBE Vector Group","hd":false}],"ip":0,"op":85.000003462121,"st":0,"bm":0},{"ddd":0,"ind":6,"ty":4,"nm":"line Outlines","tt":1,"sr":1,"ks":{"o":{"a":0,"k":100,"ix":11},"r":{"a":0,"k":0,"ix":10},"p":{"a":0,"k":[750,512,0],"ix":2},"a":{"a":0,"k":[186.75,12.25,0],"ix":1},"s":{"a":0,"k":[100,100,100],"ix":6}},"ao":0,"shapes":[{"ty":"gr","it":[{"ind":0,"ty":"sh","ix":1,"ks":{"a":0,"k":{"i":[[2.209,0],[0,0],[0,2.209],[0,0],[-2.209,0],[0,0],[0,-2.209],[0,0]],"o":[[0,0],[-2.209,0],[0,0],[0,-2.209],[0,0],[2.209,0],[0,0],[0,2.209]],"v":[[8,12],[-8,12],[-12,8],[-12,-8],[-8,-12],[8,-12],[12,-8],[12,8]],"c":true},"ix":2},"nm":"Path 1","mn":"ADBE Vector Shape - Group","hd":false},{"ty":"fl","c":{"a":0,"k":[0.349000010771,0.356999984442,0.941000007181,1],"ix":4},"o":{"a":0,"k":100,"ix":5},"r":1,"nm":"Fill 1","mn":"ADBE Vector Graphic - Fill","hd":false},{"ty":"tr","p":{"a":0,"k":[12.25,12.25],"ix":2},"a":{"a":0,"k":[0,0],"ix":1},"s":{"a":0,"k":[100,100],"ix":3},"r":{"a":0,"k":0,"ix":6},"o":{"a":0,"k":100,"ix":7},"sk":{"a":0,"k":0,"ix":4},"sa":{"a":0,"k":0,"ix":5},"nm":"Transform"}],"nm":"Group 1","np":2,"cix":2,"ix":1,"mn":"ADBE Vector Group","hd":false},{"ty":"gr","it":[{"ind":0,"ty":"sh","ix":1,"ks":{"a":0,"k":{"i":[[2.209,0],[0,0],[0,2.209],[0,0],[-2.209,0],[0,0],[0,-2.209],[0,0]],"o":[[0,0],[-2.209,0],[0,0],[0,-2.209],[0,0],[2.209,0],[0,0],[0,2.209]],"v":[[8,12],[-8,12],[-12,8],[-12,-8],[-8,-12],[8,-12],[12,-8],[12,8]],"c":true},"ix":2},"nm":"Path 1","mn":"ADBE Vector Shape - Group","hd":false},{"ty":"fl","c":{"a":0,"k":[0.349000010771,0.356999984442,0.941000007181,1],"ix":4},"o":{"a":0,"k":100,"ix":5},"r":1,"nm":"Fill 1","mn":"ADBE Vector Graphic - Fill","hd":false},{"ty":"tr","p":{"a":0,"k":[361.25,12.25],"ix":2},"a":{"a":0,"k":[0,0],"ix":1},"s":{"a":0,"k":[100,100],"ix":3},"r":{"a":0,"k":0,"ix":6},"o":{"a":0,"k":100,"ix":7},"sk":{"a":0,"k":0,"ix":4},"sa":{"a":0,"k":0,"ix":5},"nm":"Transform"}],"nm":"Group 2","np":2,"cix":2,"ix":2,"mn":"ADBE Vector Group","hd":false},{"ty":"gr","it":[{"ind":0,"ty":"sh","ix":1,"ks":{"a":1,"k":[{"i":{"x":0,"y":1},"o":{"x":0.25,"y":0},"n":"0_1_0p25_0","t":30,"s":[{"i":[[0,0],[0,0],[0,0]],"o":[[0,0],[0,0],[0,0]],"v":[[12.25,12.25],[186.75,12.25],[360.75,12.25]],"c":false}],"e":[{"i":[[0,0],[-59.406,0],[0,0]],"o":[[0,0],[58.585,0],[0,0]],"v":[[12.25,12.25],[187.75,43.25],[360.75,12.25]],"c":false}]},{"i":{"x":0.312,"y":1},"o":{"x":0.654,"y":0},"n":"0p312_1_0p654_0","t":35,"s":[{"i":[[0,0],[-59.406,0],[0,0]],"o":[[0,0],[58.585,0],[0,0]],"v":[[12.25,12.25],[187.75,43.25],[360.75,12.25]],"c":false}],"e":[{"i":[[0,0],[-59.406,0],[0,0]],"o":[[0,0],[58.585,0],[0,0]],"v":[[12.25,12.25],[187.75,-6.75],[360.75,12.25]],"c":false}]},{"i":{"x":0.477,"y":1},"o":{"x":0.37,"y":0},"n":"0p477_1_0p37_0","t":40,"s":[{"i":[[0,0],[-59.406,0],[0,0]],"o":[[0,0],[58.585,0],[0,0]],"v":[[12.25,12.25],[187.75,-6.75],[360.75,12.25]],"c":false}],"e":[{"i":[[0,0],[-59.406,0],[0,0]],"o":[[0,0],[58.585,0],[0,0]],"v":[[12.25,12.25],[188.75,24.25],[360.75,12.25]],"c":false}]},{"i":{"x":0.633,"y":1},"o":{"x":0.198,"y":0},"n":"0p633_1_0p198_0","t":43,"s":[{"i":[[0,0],[-59.406,0],[0,0]],"o":[[0,0],[58.585,0],[0,0]],"v":[[12.25,12.25],[188.75,24.25],[360.75,12.25]],"c":false}],"e":[{"i":[[0,0],[-59.406,0],[0,0]],"o":[[0,0],[58.585,0],[0,0]],"v":[[12.25,12.25],[188.75,13.25],[360.75,12.25]],"c":false}]},{"t":45.0000018328876}],"ix":2},"nm":"Path 1","mn":"ADBE Vector Shape - Group","hd":false},{"ty":"st","c":{"a":0,"k":[0.26699999641,0.26699999641,0.26699999641,1],"ix":3},"o":{"a":0,"k":100,"ix":4},"w":{"a":0,"k":6,"ix":5},"lc":1,"lj":1,"ml":10,"nm":"Stroke 1","mn":"ADBE Vector Graphic - Stroke","hd":false},{"ty":"tr","p":{"a":0,"k":[0,0],"ix":2},"a":{"a":0,"k":[0,0],"ix":1},"s":{"a":0,"k":[100,100],"ix":3},"r":{"a":0,"k":0,"ix":6},"o":{"a":0,"k":100,"ix":7},"sk":{"a":0,"k":0,"ix":4},"sa":{"a":0,"k":0,"ix":5},"nm":"Transform"}],"nm":"Group 3","np":2,"cix":2,"ix":3,"mn":"ADBE Vector Group","hd":false}],"ip":0,"op":85.000003462121,"st":0,"bm":0},{"ddd":0,"ind":10,"ty":1,"nm":"bg","sr":1,"ks":{"o":{"a":0,"k":100,"ix":11},"r":{"a":0,"k":0,"ix":10},"p":{"a":0,"k":[750,400,0],"ix":2},"a":{"a":0,"k":[400,300,0],"ix":1},"s":{"a":0,"k":[188,133.333,100],"ix":6}},"ao":0,"sw":800,"sh":600,"sc":"#ffffff","ip":0,"op":85.000003462121,"st":0,"bm":0}],"markers":[]}